interactionfreemongodb/MongoDBContext.py
interactionfreemongodb/Storage.py
interactionfreemongodb/__init__.py
interactionfreemongodb/app.py
interactionfreemongodb-1.1.2.dist-info/LICENSE
interactionfreemongodb-1.1.2.dist-info/METADATA
interactionfreemongodb-1.1.2.dist-info/WHEEL
interactionfreemongodb-1.1.2.dist-info/top_level.txt
interactionfreemongodb-1.1.2.dist-info/RECORD
