Metadata-Version: 2.1
Name: interactionfreemongodb
Version: 1.1.2
Summary: A storage service for InteractionFree based on MongoDB.
Home-page: https://github.com/hwaipy/InteractionFreeMongoDB
Author: Hwaipy
Author-email: hwaipy@gmail.com
License: gpl-3.0
Download-URL: https://github.com/hwaipy/InteractionFreeMongoDB/archive/v1.1.2.tar.gz
Keywords: interactionfreepy,service,mongodb,rpc
Platform: UNKNOWN
Classifier: Development Status :: 5 - Production/Stable
Classifier: Intended Audience :: Developers
Classifier: Intended Audience :: End Users/Desktop
Classifier: License :: OSI Approved :: GNU General Public License v3 (GPLv3)
Classifier: Programming Language :: Python :: 3
Classifier: Programming Language :: Python :: 3.6
Classifier: Programming Language :: Python :: 3.7
Classifier: Programming Language :: Python :: 3.8
Requires-Python: >=3.6
Requires-Dist: interactionfreepy
Requires-Dist: motor
Requires-Dist: pytz
